keyboard/fpga/counter.v
/*
* Basic counter module
*
* Has enable, reset, and clock inputs
*
* max_val output goes high **after** MAX_VALUE has been reached and the
* counter has been reset to 0. So, when max_val is high, the counter is
* currently at 0, except when reset by rst
*/

module counter #(
    parameter MAX_VALUE = 1,
    parameter BIT_WIDTH = 1
) (
    input en,
    clk,
    rst,

    output reg                 max_val,
    output reg [BIT_WIDTH-1:0] count
);

  always @(posedge rst) begin
    max_val <= 0;
    count   <= 0;
  end

  always @(posedge clk) begin
    if (en && !rst) begin
      count <= count + 1;
      // MAX_VALUE reached
      if (count == MAX_VALUE - 1) begin
        max_val <= 1;
        count   <= 0;
      end else begin
        max_val <= 0;
      end
    end
  end

endmodule

keyboard/fpga/testbenches/counter_tb.v
/*
* A testbench for the counter module
*/

`timescale 1 ns / 1 ps

module counter_tb ();
  reg        clk = 0;
  reg        en = 0;
  reg        rst = 0;
  wire [4:0] count;
  wire       max_val;

  counter #(
      .MAX_VALUE(16),
      .BIT_WIDTH(5)
  ) c (
      .clk(clk),
      .en(en),
      .rst(rst),
      .count(count),
      .max_val(max_val)
  );

  always begin
    #1 clk = ~clk;
  end

  initial begin
    #1 rst = 1;
    #1 rst = 0;
    en = 1;
    #100 $finish;
  end

  initial begin
    $dumpfile("counter.vcd");
    $dumpvars(0, counter_tb);
  end

endmodule

keyboard/fpga/counter.vcd
$date
	Thu Jul 20 14:03:54 2023
$end
$version
	Icarus Verilog
$end
$timescale
	1ps
$end
$scope module counter_tb $end
$var wire 1 ! max_val $end
$var wire 5 " count [4:0] $end
$var reg 1 # clk $end
$var reg 1 $ en $end
$var reg 1 % rst $end
$scope module c $end
$var wire 1 # clk $end
$var wire 1 $ en $end
$var wire 1 % rst $end
$var parameter 32 & BIT_WIDTH $end
$var parameter 32 ' MAX_VALUE $end
$var reg 5 ( count [4:0] $end
$var reg 1 ! max_val $end
$upscope $end
$upscope $end
$enddefinitions $end
$comment Show the parameter values. $end
$dumpall
b10000 '
b101 &
$end
#0
$dumpvars
bx (
0%
0$
0#
bx "
x!
$end
#1000
b0 "
b0 (
0!
1%
1#
#2000
1$
0%
0#
#3000
b1 "
b1 (
1#
#4000
0#
#5000
b10 "
b10 (
1#
#6000
0#
#7000
b11 "
b11 (
1#
#8000
0#
#9000
b100 "
b100 (
1#
#10000
0#
#11000
b101 "
b101 (
1#
#12000
0#
#13000
b110 "
b110 (
1#
#14000
0#
#15000
b111 "
b111 (
1#
#16000
0#
#17000
b1000 "
b1000 (
1#
#18000
0#
#19000
b1001 "
b1001 (
1#
#20000
0#
#21000
b1010 "
b1010 (
1#
#22000
0#
#23000
b1011 "
b1011 (
1#
#24000
0#
#25000
b1100 "
b1100 (
1#
#26000
0#
#27000
b1101 "
b1101 (
1#
#28000
0#
#29000
b1110 "
b1110 (
1#
#30000
0#
#31000
b1111 "
b1111 (
1#
#32000
0#
#33000
b10000 "
b10000 (
1#
#34000
0#
#35000
1!
b0 "
b0 (
1#
#36000
0#
#37000
0!
b1 "
b1 (
1#
#38000
0#
#39000
b10 "
b10 (
1#
#40000
0#
#41000
b11 "
b11 (
1#
#42000
0#
#43000
b100 "
b100 (
1#
#44000
0#
#45000
b101 "
b101 (
1#
#46000
0#
#47000
b110 "
b110 (
1#
#48000
0#
#49000
b111 "
b111 (
1#
#50000
0#
#51000
b1000 "
b1000 (
1#
#52000
0#
#53000
b1001 "
b1001 (
1#
#54000
0#
#55000
b1010 "
b1010 (
1#
#56000
0#
#57000
b1011 "
b1011 (
1#
#58000
0#
#59000
b1100 "
b1100 (
1#
#60000
0#
#61000
b1101 "
b1101 (
1#
#62000
0#
#63000
b1110 "
b1110 (
1#
#64000
0#
#65000
b1111 "
b1111 (
1#
#66000
0#
#67000
b10000 "
b10000 (
1#
#68000
0#
#69000
1!
b0 "
b0 (
1#
#70000
0#
#71000
0!
b1 "
b1 (
1#
#72000
0#
#73000
b10 "
b10 (
1#
#74000
0#
#75000
b11 "
b11 (
1#
#76000
0#
#77000
b100 "
b100 (
1#
#78000
0#
#79000
b101 "
b101 (
1#
#80000
0#
#81000
b110 "
b110 (
1#
#82000
0#
#83000
b111 "
b111 (
1#
#84000
0#
#85000
b1000 "
b1000 (
1#
#86000
0#
#87000
b1001 "
b1001 (
1#
#88000
0#
#89000
b1010 "
b1010 (
1#
#90000
0#
#91000
b1011 "
b1011 (
1#
#92000
0#
#93000
b1100 "
b1100 (
1#
#94000
0#
#95000
b1101 "
b1101 (
1#
#96000
0#
#97000
b1110 "
b1110 (
1#
#98000
0#
#99000
b1111 "
b1111 (
1#
#100000
0#
#101000
b10000 "
b10000 (
1#
