keyboard/fpga/counter.v
/*
* Basic counter module
*
* Has enable, reset, and clock inputs
*
* max_val output goes high **after** MAX_VALUE has been reached and the
* counter has been reset to 0. So, when max_val is high, the counter is
* currently at 0, except when reset by rst
*/

module counter #(
    parameter MAX_VALUE = 1,
    parameter BIT_WIDTH = 1
) (
    input en,
    clk,
    rst,

    output reg                 max_val,
    output reg [BIT_WIDTH-1:0] count
);

  always @(posedge rst) begin
    max_val <= 0;
    count   <= 0;
  end

  always @(posedge clk) begin
    if (en && !rst) begin
      count <= count + 1;
      // MAX_VALUE reached
      if (count == MAX_VALUE - 1) begin
        max_val <= 1;
        count   <= 0;
      end else begin
        max_val <= 0;
      end
    end
  end

endmodule

keyboard/fpga/initial_response.v
/*
* This module controls the initial response to the keyboard necessary for the
* resetting of the PERIBOARD ps/2 keyboard. (sends code 0xFF)
*
* inputs : reset_required should go high when the keyboard sends code 0xAA and
*           code 0xFF needs to be sent
*          clk is the clock signal
*          rst will reset the module
*/

module initial_response #(
    parameter MAX_COUNT = 1,  // number of clk ticks to keep ps2_clk low
    parameter BIT_WIDTH = 1   // number of bits needed for MAX_COUNT
) (
    input reset_required,  // code 0xAA recieved
    clk,
    rst,  // reset count to 0

    output reg ps2_clk_pulldown,
    output reg ps2_data_pulldown
);

  reg                  c1_en;
  reg                  c1_rst;
  wire                 c1_max_val;
  wire [BIT_WIDTH-1:0] c1_count;

  counter #(
      .BIT_WIDTH(BIT_WIDTH),
      .MAX_VALUE(MAX_COUNT)
  ) c1 (
      .en(c1_en),
      .clk(clk),
      .rst(c1_rst),
      .max_val(c1_max_val),
      .count(c1_count)
  );

  always @(posedge clk) begin
    // always reset counter if this module is reset
    c1_rst <= rst;
    if (rst) begin
      c1_en <= 0;
      ps2_clk_pulldown <= 0;
      ps2_data_pulldown <= 0;
    end
    // start counting and pull down ps2_clk
    if (reset_required) begin
      c1_en <= 1;
      ps2_clk_pulldown <= 1;
    end

    // while counting, count
    if (c1_en) begin
      // if reached MAX_COUNT, stop counting
      if (c1_max_val) begin
        c1_en <= 0;
        c1_rst <= 1;
        ps2_clk_pulldown <= 0;
      end
    end

    // never want to pull data line low
    ps2_data_pulldown <= 0;
  end

endmodule

keyboard/fpga/initial_response_tb.v
/*
* A testbench for the initial_response module
*/

`timescale 1 ns / 1 ps

module initial_response_tb ();
  reg  clk = 0;
  reg  rst = 0;
  reg  reset_required = 0;
  wire ps2_clk_pull_down;
  wire ps2_data_pull_down;

  initial_response #(
      .MAX_COUNT(16),
      .BIT_WIDTH(5)
  ) r (
      .reset_required(reset_required),
      .clk(clk),
      .rst(rst),
      .ps2_clk_pulldown(ps2_clk_pull_down),
      .ps2_data_pulldown(ps2_data_pull_down)
  );

  always begin
    #1 clk = ~clk;
  end

  initial begin
    #1 rst = 1;
    #1 rst = 0;
    reset_required = 1;
    #2 reset_required = 0;
    #50 $finish;
  end

  initial begin
    $dumpfile("initial_response.vcd");
    $dumpvars(0, initial_response_tb);
  end

endmodule

keyboard/fpga/initial_response.vcd
$date
	Thu Jul 20 14:56:45 2023
$end
$version
	Icarus Verilog
$end
$timescale
	1ps
$end
$scope module initial_response_tb $end
$var wire 1 ! ps2_data_pull_down $end
$var wire 1 " ps2_clk_pull_down $end
$var reg 1 # clk $end
$var reg 1 $ reset_required $end
$var reg 1 % rst $end
$scope module r $end
$var wire 1 # clk $end
$var wire 1 $ reset_required $end
$var wire 1 % rst $end
$var wire 1 & c1_max_val $end
$var wire 5 ' c1_count [4:0] $end
$var parameter 32 ( BIT_WIDTH $end
$var parameter 32 ) MAX_COUNT $end
$var reg 1 * c1_en $end
$var reg 1 + c1_rst $end
$var reg 1 " ps2_clk_pulldown $end
$var reg 1 ! ps2_data_pulldown $end
$scope module c1 $end
$var wire 1 # clk $end
$var wire 1 * en $end
$var wire 1 + rst $end
$var parameter 32 , BIT_WIDTH $end
$var parameter 32 - MAX_VALUE $end
$var reg 5 . count [4:0] $end
$var reg 1 & max_val $end
$upscope $end
$upscope $end
$upscope $end
$enddefinitions $end
$comment Show the parameter values. $end
$dumpall
b10000 -
b101 ,
b10000 )
b101 (
$end
#0
$dumpvars
bx .
x+
x*
bx '
x&
0%
0$
0#
x"
x!
$end
#1000
b0 '
b0 .
0&
0!
0"
0*
1+
1%
1#
#2000
1$
0%
0#
#3000
1"
1*
0+
1#
#4000
0#
0$
#5000
b1 '
b1 .
1#
#6000
0#
#7000
b10 '
b10 .
1#
#8000
0#
#9000
b11 '
b11 .
1#
#10000
0#
#11000
b100 '
b100 .
1#
#12000
0#
#13000
b101 '
b101 .
1#
#14000
0#
#15000
b110 '
b110 .
1#
#16000
0#
#17000
b111 '
b111 .
1#
#18000
0#
#19000
b1000 '
b1000 .
1#
#20000
0#
#21000
b1001 '
b1001 .
1#
#22000
0#
#23000
b1010 '
b1010 .
1#
#24000
0#
#25000
b1011 '
b1011 .
1#
#26000
0#
#27000
b1100 '
b1100 .
1#
#28000
0#
#29000
b1101 '
b1101 .
1#
#30000
0#
#31000
b1110 '
b1110 .
1#
#32000
0#
#33000
b1111 '
b1111 .
1#
#34000
0#
#35000
b10000 '
b10000 .
1#
#36000
0#
#37000
1&
b0 '
b0 .
1#
#38000
0#
#39000
0&
b0 '
b0 .
0"
1+
0*
1#
#40000
0#
#41000
0+
1#
