keyboard/fpga/counter.v
/*
* Basic counter module
*
* Has enable, reset, and clock inputs
*
* max_val output goes high **after** MAX_VALUE has been reached and the
* counter has been reset to 0. So, when max_val is high, the counter is
* currently at 0, except when reset by rst
*/

module counter #(
    parameter MAX_VALUE = 1,
    parameter BIT_WIDTH = 1
) (
    input en,
    clk,
    rst,

    output reg                 max_val,
    output reg [BIT_WIDTH-1:0] count
);

  always @(posedge rst) begin
    max_val <= 0;
    count   <= 0;
  end

  always @(posedge clk) begin
    if (en && !rst) begin
      count <= count + 1;
      // MAX_VALUE reached
      if (count == MAX_VALUE - 1) begin
        max_val <= 1;
        count   <= 0;
      end else begin
        max_val <= 0;
      end
    end
  end

endmodule

keyboard/fpga/receiver.v
/*
* This module contains the "receiver" used to translate the ps/2 keyboard data
* into a format that the rest of the system can use
*/

module receiver (
    input ps2_data,
    input ps2_clk,
    input rst,

    output reg [10:0] data,
    output reg        data_latch,      // used to latch data into other modules
    output reg        reset_required,  // used when 0xAA received
    output reg        release_key,     // used when 0xF0 received
    output reg        extended_code    // used when 0xE0 received
);

  reg        c1_en = 1;
  wire       c1_max_val;
  wire [3:0] c1_count;

  counter #(
      .MAX_VALUE(11),
      .BIT_WIDTH(4)
  ) c1 (
      .en(c1_en),
      .clk(ps2_clk),
      .rst(rst),
      .max_val(c1_max_val),
      .count(c1_count)
  );

  always @(negedge ps2_clk, posedge c1_max_val) begin
    // shift in new bit
    if (!ps2_clk) begin
      data <= data << 1;
      data[0] <= ps2_data;
    end

    // set appropriate signal if 11 bits clocked in
    // bits come in lsb first, so data[8] is lsb
    if (c1_max_val) begin
      if (data[9:2] == 8'h55) begin  // 0xAA is actual code, but 0x55 cause of bit ordering
        reset_required <= 1;
      end else if (data[9:2] == 8'h0F) begin  // 0xF0
        release_key <= 1;
      end else if (data[9:2] == 8'h07) begin  // 0xE0
        extended_code <= 1;
      end else begin
        data_latch <= 1;
      end

      // else set all output signals to 0
    end else begin
      reset_required <= 0;
      release_key <= 0;
      extended_code <= 0;
      data_latch <= 0;
    end
  end

endmodule

keyboard/fpga/testbenches/receiver_tb.v
/*
* A testbench for the initial_response module
*/

`timescale 1 ns / 1 ps

module receiver_tb ();
  reg            ps2_data = 1;
  reg            ps2_clock = 1;
  reg            rst = 0;
  wire    [10:0] data;
  wire           data_latch;
  wire           reset_required;
  wire           release_key;
  wire           extended_code;

  reg     [0:10] read_data      [0:3];
  integer        i;
  integer        j;

  receiver #() r (
      .ps2_data(ps2_data),
      .ps2_clk(ps2_clock),
      .rst(rst),
      .data(data),
      .data_latch(data_latch),
      .reset_required(reset_required),
      .release_key(release_key),
      .extended_code(extended_code)
  );

  initial begin
    #1 rst = 1;
    #1 rst = 0;

    $readmemb("testbenches/io/receiver_io.txt", read_data);

    for (i = 0; i < 4; i = i + 1) begin
      for (j = 0; j < 11; j = j + 1) begin
        #2 ps2_data = read_data[i][j];
        #1 ps2_clock = 0;
        #1 ps2_clock = 1;
        #4;
      end
      #10;
    end

    #10 $finish;
  end

  initial begin
    $dumpfile("receiver.vcd");
    $dumpvars(0, receiver_tb);
  end

endmodule

keyboard/fpga/waveforms/receiver.vcd
$date
	Thu Jul 20 18:20:25 2023
$end
$version
	Icarus Verilog
$end
$timescale
	1ps
$end
$scope module receiver_tb $end
$var wire 1 ! ps2_clk $end
$var wire 1 " reset_required $end
$var wire 1 # release_key $end
$var wire 1 $ extended_code $end
$var wire 1 % data_latch $end
$var wire 11 & data [10:0] $end
$var reg 1 ' ps2_clock $end
$var reg 1 ( ps2_data $end
$var reg 1 ) rst $end
$var integer 32 * i [31:0] $end
$var integer 32 + j [31:0] $end
$scope module r $end
$var wire 1 ! ps2_clk $end
$var wire 1 ( ps2_data $end
$var wire 1 ) rst $end
$var wire 1 , c1_max_val $end
$var wire 4 - c1_count [3:0] $end
$var reg 1 . c1_en $end
$var reg 11 / data [10:0] $end
$var reg 1 % data_latch $end
$var reg 1 $ extended_code $end
$var reg 1 # release_key $end
$var reg 1 " reset_required $end
$scope module c1 $end
$var wire 1 ! clk $end
$var wire 1 . en $end
$var wire 1 ) rst $end
$var parameter 32 0 BIT_WIDTH $end
$var parameter 32 1 MAX_VALUE $end
$var reg 4 2 count [3:0] $end
$var reg 1 , max_val $end
$upscope $end
$upscope $end
$upscope $end
$enddefinitions $end
$comment Show the parameter values. $end
$dumpall
b1011 1
b100 0
$end
#0
$dumpvars
bx 2
bx /
1.
bx -
x,
bx +
bx *
0)
1(
1'
bx &
x%
x$
x#
x"
z!
$end
#1000
b0 -
b0 2
0,
1)
#2000
b0 +
b0 *
0)
#5000
0'
#6000
1'
#10000
b1 +
#13000
0'
#14000
1'
#18000
b10 +
#21000
0'
#22000
1'
#26000
b11 +
#28000
0(
#29000
0'
#30000
1'
#34000
b100 +
#36000
1(
#37000
0'
#38000
1'
#42000
b101 +
#44000
0(
#45000
0'
#46000
1'
#50000
b110 +
#52000
1(
#53000
0'
#54000
1'
#58000
b111 +
#60000
0(
#61000
0'
#62000
1'
#66000
b1000 +
#68000
1(
#69000
0'
#70000
1'
#74000
b1001 +
#76000
0(
#77000
0'
#78000
1'
#82000
b1010 +
#85000
0'
#86000
1'
#90000
b1011 +
#100000
b0 +
b1 *
#102000
1(
#103000
0'
#104000
1'
#108000
b1 +
#111000
0'
#112000
1'
#116000
b10 +
#118000
0(
#119000
0'
#120000
1'
#124000
b11 +
#126000
1(
#127000
0'
#128000
1'
#132000
b100 +
#134000
0(
#135000
0'
#136000
1'
#140000
b101 +
#143000
0'
#144000
1'
#148000
b110 +
#150000
1(
#151000
0'
#152000
1'
#156000
b111 +
#159000
0'
#160000
1'
#164000
b1000 +
#167000
0'
#168000
1'
#172000
b1001 +
#174000
0(
#175000
0'
#176000
1'
#180000
b1010 +
#183000
0'
#184000
1'
#188000
b1011 +
#198000
b0 +
b10 *
#200000
1(
#201000
0'
#202000
1'
#206000
b1 +
#209000
0'
#210000
1'
#214000
b10 +
#217000
0'
#218000
1'
#222000
b11 +
#225000
0'
#226000
1'
#230000
b100 +
#233000
0'
#234000
1'
#238000
b101 +
#241000
0'
#242000
1'
#246000
b110 +
#248000
0(
#249000
0'
#250000
1'
#254000
b111 +
#257000
0'
#258000
1'
#262000
b1000 +
#265000
0'
#266000
1'
#270000
b1001 +
#273000
0'
#274000
1'
#278000
b1010 +
#281000
0'
#282000
1'
#286000
b1011 +
#296000
b0 +
b11 *
#298000
1(
#299000
0'
#300000
1'
#304000
b1 +
#306000
0(
#307000
0'
#308000
1'
#312000
b10 +
#314000
1(
#315000
0'
#316000
1'
#320000
b11 +
#323000
0'
#324000
1'
#328000
b100 +
#331000
0'
#332000
1'
#336000
b101 +
#338000
0(
#339000
0'
#340000
1'
#344000
b110 +
#347000
0'
#348000
1'
#352000
b111 +
#355000
0'
#356000
1'
#360000
b1000 +
#363000
0'
#364000
1'
#368000
b1001 +
#371000
0'
#372000
1'
#376000
b1010 +
#379000
0'
#380000
1'
#384000
b1011 +
#394000
b100 *
