keyboard/fpga/counter.v
/*
* Basic counter module
*
* Has enable, reset, and clock inputs
*
* max_val output goes high **after** MAX_VALUE has been reached and the
* counter has been reset to 0. So, when max_val is high, the counter is
* currently at 0, except when reset by rst
*/

module counter #(
    parameter MAX_VALUE = 1,
    parameter BIT_WIDTH = 1
) (
    input en,
    clk,
    rst,

    output reg                 max_val,
    output reg [BIT_WIDTH-1:0] count
);

  always @(posedge rst) begin
    max_val <= 0;
    count   <= 0;
  end

  always @(posedge clk) begin
    if (en && !rst) begin
      count <= count + 1;
      // MAX_VALUE reached
      if (count == MAX_VALUE - 1) begin
        max_val <= 1;
        count   <= 0;
      end else begin
        max_val <= 0;
      end
    end
  end

endmodule

keyboard/fpga/receiver.v
/*
* This module contains the "receiver" used to translate the ps/2 keyboard data
* into a format that the rest of the system can use
*/

module receiver (
    input ps2_data,
    input ps2_clk,
    input rst,

    output reg [10:0] data,
    output reg        data_latch,      // used to latch data into other modules
    output reg        reset_required,  // used when 0xAA received
    output reg        release_key,     // used when 0xF0 received
    output reg        extended_code    // used when 0xE0 received
);

  reg        c1_en = 1;
  wire       c1_max_val;
  wire [3:0] c1_count;

  counter #(
      .MAX_VALUE(11),
      .BIT_WIDTH(4)
  ) c1 (
      .en(c1_en),
      .clk(ps2_clk),
      .rst(rst),
      .max_val(c1_max_val),
      .count(c1_count)
  );

  always @(negedge ps2_clk, posedge c1_max_val) begin
    // shift in new bit
    if (!ps2_clk) begin
      data <= data << 1;
      data[0] <= ps2_data;
    end

    // set appropriate signal if 11 bits clocked in
    // bits come in lsb first, so data[8] is lsb
    if (c1_max_val) begin
      if (data[9:2] == 8'h55) begin  // 0xAA is actual code, but 0x55 cause of bit ordering
        reset_required <= 1;
      end else if (data[9:2] == 8'h0F) begin  // 0xF0
        release_key <= 1;
      end else if (data[9:2] == 8'h07) begin  // 0xE0
        extended_code <= 1;
      end else begin
        data_latch <= 1;
      end

      // else set all output signals to 0
    end else begin
      reset_required <= 0;
      release_key <= 0;
      extended_code <= 0;
      data_latch <= 0;
    end
  end

endmodule

keyboard/fpga/testbenches/receiver_tb.v
/*
* A testbench for the initial_response module
*/

`timescale 1 ns / 1 ps

module receiver_tb ();
  reg            ps2_data = 1;
  reg            ps2_clock = 1;
  reg            rst = 0;
  wire    [10:0] data;
  wire           data_latch;
  wire           reset_required;
  wire           release_key;
  wire           extended_code;

  reg     [0:10] read_data      [0:3];
  integer        i;
  integer        j;

  receiver #() r (
      .ps2_data(ps2_data),
      .ps2_clk(ps2_clock),
      .rst(rst),
      .data(data),
      .data_latch(data_latch),
      .reset_required(reset_required),
      .release_key(release_key),
      .extended_code(extended_code)
  );

  initial begin
    #1 rst = 1;
    #1 rst = 0;

    $readmemb("testbenches/io/receiver_io.txt", read_data);

    for (i = 0; i < 4; i = i + 1) begin
      for (j = 0; j < 11; j = j + 1) begin
        #2 ps2_data = read_data[i][j];
        #1 ps2_clock = 0;
        #1 ps2_clock = 1;
        #4;
      end
      #10;
    end

    #10 $finish;
  end

  initial begin
    $dumpfile("receiver.vcd");
    $dumpvars(0, receiver_tb);
  end

endmodule

keyboard/fpga/waveforms/receiver.vcd
$date
	Fri Jul 21 22:56:22 2023
$end
$version
	Icarus Verilog
$end
$timescale
	1ps
$end
$scope module receiver_tb $end
$var wire 1 ! reset_required $end
$var wire 1 " release_key $end
$var wire 1 # extended_code $end
$var wire 1 $ data_latch $end
$var wire 11 % data [10:0] $end
$var reg 1 & ps2_clock $end
$var reg 1 ' ps2_data $end
$var reg 1 ( rst $end
$var integer 32 ) i [31:0] $end
$var integer 32 * j [31:0] $end
$scope module r $end
$var wire 1 & ps2_clk $end
$var wire 1 ' ps2_data $end
$var wire 1 ( rst $end
$var wire 1 + c1_max_val $end
$var wire 4 , c1_count [3:0] $end
$var reg 1 - c1_en $end
$var reg 11 . data [10:0] $end
$var reg 1 $ data_latch $end
$var reg 1 # extended_code $end
$var reg 1 " release_key $end
$var reg 1 ! reset_required $end
$scope module c1 $end
$var wire 1 & clk $end
$var wire 1 - en $end
$var wire 1 ( rst $end
$var parameter 32 / BIT_WIDTH $end
$var parameter 32 0 MAX_VALUE $end
$var reg 4 1 count [3:0] $end
$var reg 1 + max_val $end
$upscope $end
$upscope $end
$upscope $end
$enddefinitions $end
$comment Show the parameter values. $end
$dumpall
b1011 0
b100 /
$end
#0
$dumpvars
bx 1
bx .
1-
bx ,
0+
bx *
bx )
0(
1'
1&
bx %
x$
x#
x"
x!
$end
#1000
b0 ,
b0 1
1(
#2000
b0 *
b0 )
0(
#4000
0'
#5000
0$
0#
0"
0!
bx0 %
bx0 .
0&
#6000
b1 ,
b1 1
1&
#10000
b1 *
#13000
bx00 %
bx00 .
0&
#14000
b10 ,
b10 1
1&
#18000
b10 *
#20000
1'
#21000
bx001 %
bx001 .
0&
#22000
b11 ,
b11 1
1&
#26000
b11 *
#28000
0'
#29000
bx0010 %
bx0010 .
0&
#30000
b100 ,
b100 1
1&
#34000
b100 *
#36000
1'
#37000
bx00101 %
bx00101 .
0&
#38000
b101 ,
b101 1
1&
#42000
b101 *
#44000
0'
#45000
bx001010 %
bx001010 .
0&
#46000
b110 ,
b110 1
1&
#50000
b110 *
#52000
1'
#53000
bx0010101 %
bx0010101 .
0&
#54000
b111 ,
b111 1
1&
#58000
b111 *
#60000
0'
#61000
bx00101010 %
bx00101010 .
0&
#62000
b1000 ,
b1000 1
1&
#66000
b1000 *
#68000
1'
#69000
bx001010101 %
bx001010101 .
0&
#70000
b1001 ,
b1001 1
1&
#74000
b1001 *
#77000
bx0010101011 %
bx0010101011 .
0&
#78000
b1010 ,
b1010 1
1&
#82000
b1010 *
#85000
b101010111 %
b101010111 .
0&
#86000
1!
1+
b0 ,
b0 1
1&
#90000
b1011 *
#100000
b0 *
b1 )
#102000
0'
#103000
b1010101110 %
b1010101110 .
0&
#104000
0+
b1 ,
b1 1
1&
#108000
b1 *
#111000
0!
b10101011100 %
b10101011100 .
0&
#112000
b10 ,
b10 1
1&
#116000
b10 *
#118000
1'
#119000
b1010111001 %
b1010111001 .
0&
#120000
b11 ,
b11 1
1&
#124000
b11 *
#127000
b10101110011 %
b10101110011 .
0&
#128000
b100 ,
b100 1
1&
#132000
b100 *
#135000
b1011100111 %
b1011100111 .
0&
#136000
b101 ,
b101 1
1&
#140000
b101 *
#142000
0'
#143000
b10111001110 %
b10111001110 .
0&
#144000
b110 ,
b110 1
1&
#148000
b110 *
#151000
b1110011100 %
b1110011100 .
0&
#152000
b111 ,
b111 1
1&
#156000
b111 *
#158000
1'
#159000
b11100111001 %
b11100111001 .
0&
#160000
b1000 ,
b1000 1
1&
#164000
b1000 *
#166000
0'
#167000
b11001110010 %
b11001110010 .
0&
#168000
b1001 ,
b1001 1
1&
#172000
b1001 *
#174000
1'
#175000
b10011100101 %
b10011100101 .
0&
#176000
b1010 ,
b1010 1
1&
#180000
b1010 *
#183000
b111001011 %
b111001011 .
0&
#184000
1$
1+
b0 ,
b0 1
1&
#188000
b1011 *
#198000
b0 *
b10 )
#200000
0'
#201000
b1110010110 %
b1110010110 .
0&
#202000
0+
b1 ,
b1 1
1&
#206000
b1 *
#209000
0$
b11100101100 %
b11100101100 .
0&
#210000
b10 ,
b10 1
1&
#214000
b10 *
#217000
b11001011000 %
b11001011000 .
0&
#218000
b11 ,
b11 1
1&
#222000
b11 *
#225000
b10010110000 %
b10010110000 .
0&
#226000
b100 ,
b100 1
1&
#230000
b100 *
#233000
b101100000 %
b101100000 .
0&
#234000
b101 ,
b101 1
1&
#238000
b101 *
#240000
1'
#241000
b1011000001 %
b1011000001 .
0&
#242000
b110 ,
b110 1
1&
#246000
b110 *
#249000
b10110000011 %
b10110000011 .
0&
#250000
b111 ,
b111 1
1&
#254000
b111 *
#257000
b1100000111 %
b1100000111 .
0&
#258000
b1000 ,
b1000 1
1&
#262000
b1000 *
#265000
b11000001111 %
b11000001111 .
0&
#266000
b1001 ,
b1001 1
1&
#270000
b1001 *
#273000
b10000011111 %
b10000011111 .
0&
#274000
b1010 ,
b1010 1
1&
#278000
b1010 *
#281000
b111111 %
b111111 .
0&
#282000
1"
1+
b0 ,
b0 1
1&
#286000
b1011 *
#296000
b0 *
b11 )
#298000
0'
#299000
b1111110 %
b1111110 .
0&
#300000
0+
b1 ,
b1 1
1&
#304000
b1 *
#307000
0"
b11111100 %
b11111100 .
0&
#308000
b10 ,
b10 1
1&
#312000
b10 *
#315000
b111111000 %
b111111000 .
0&
#316000
b11 ,
b11 1
1&
#320000
b11 *
#323000
b1111110000 %
b1111110000 .
0&
#324000
b100 ,
b100 1
1&
#328000
b100 *
#331000
b11111100000 %
b11111100000 .
0&
#332000
b101 ,
b101 1
1&
#336000
b101 *
#339000
b11111000000 %
b11111000000 .
0&
#340000
b110 ,
b110 1
1&
#344000
b110 *
#346000
1'
#347000
b11110000001 %
b11110000001 .
0&
#348000
b111 ,
b111 1
1&
#352000
b111 *
#355000
b11100000011 %
b11100000011 .
0&
#356000
b1000 ,
b1000 1
1&
#360000
b1000 *
#363000
b11000000111 %
b11000000111 .
0&
#364000
b1001 ,
b1001 1
1&
#368000
b1001 *
#370000
0'
#371000
b10000001110 %
b10000001110 .
0&
#372000
b1010 ,
b1010 1
1&
#376000
b1010 *
#378000
1'
#379000
b11101 %
b11101 .
0&
#380000
1#
1+
b0 ,
b0 1
1&
#384000
b1011 *
#394000
b100 )
