keyboard/fpga/receiver.v
/*
* This module contains the "receiver" used to translate the ps/2 keyboard data
* into a format that the rest of the system can use
*/

module receiver (
    input ps2_data,
    input ps2_clk,

    output reg reset_required  // used when 0xAA received
);
  reg [10:0] data;

  always @(negedge ps2_clk) begin
    data <= {data[9:0], ps2_data};
  end

  always @* begin
    if (data == 11'b00101010111) begin
      reset_required <= 1;
    end else begin
      reset_required <= 0;
    end
  end

endmodule

keyboard/fpga/testbenches/receiver_tb.v
/*
* A testbench for the initial_response module
*/

`timescale 1 ns / 1 ps

module receiver_tb ();
  reg            ps2_data = 1;
  reg            ps2_clock = 1;
  wire           reset_required;

  reg     [0:10] read_data      [0:3];
  integer        i;
  integer        j;

  receiver #() r (
      .ps2_data(ps2_data),
      .ps2_clk(ps2_clock),
      .reset_required(reset_required)
  );

  initial begin
    $readmemb("testbenches/io/receiver_io.txt", read_data);

    for (i = 0; i < 4; i = i + 1) begin
      for (j = 0; j < 11; j = j + 1) begin
        #2 ps2_data = read_data[i][j];
        #1 ps2_clock = 0;
        #1 ps2_clock = 1;
        #4;
      end
      #10;
    end

    #10 $finish;
  end

  initial begin
    $dumpfile("receiver.vcd");
    $dumpvars(0, receiver_tb);
  end

endmodule

keyboard/fpga/waveforms/receiver.vcd
$date
	Sun Jul 23 00:07:58 2023
$end
$version
	Icarus Verilog
$end
$timescale
	1ps
$end
$scope module receiver_tb $end
$var wire 1 ! reset_required $end
$var reg 1 " ps2_clock $end
$var reg 1 # ps2_data $end
$var integer 32 $ i [31:0] $end
$var integer 32 % j [31:0] $end
$scope module r $end
$var wire 1 " ps2_clk $end
$var wire 1 # ps2_data $end
$var reg 11 & data [10:0] $end
$var reg 1 ! reset_required $end
$upscope $end
$upscope $end
$enddefinitions $end
$comment Show the parameter values. $end
$dumpall
$end
#0
$dumpvars
bx &
b0 %
b0 $
1#
1"
x!
$end
#2000
0#
#3000
0!
bx0 &
0"
#4000
1"
#8000
b1 %
#11000
bx00 &
0"
#12000
1"
#16000
b10 %
#18000
1#
#19000
bx001 &
0"
#20000
1"
#24000
b11 %
#26000
0#
#27000
bx0010 &
0"
#28000
1"
#32000
b100 %
#34000
1#
#35000
bx00101 &
0"
#36000
1"
#40000
b101 %
#42000
0#
#43000
bx001010 &
0"
#44000
1"
#48000
b110 %
#50000
1#
#51000
bx0010101 &
0"
#52000
1"
#56000
b111 %
#58000
0#
#59000
bx00101010 &
0"
#60000
1"
#64000
b1000 %
#66000
1#
#67000
bx001010101 &
0"
#68000
1"
#72000
b1001 %
#75000
bx0010101011 &
0"
#76000
1"
#80000
b1010 %
#83000
1!
b101010111 &
0"
#84000
1"
#88000
b1011 %
#98000
b0 %
b1 $
#100000
0#
#101000
0!
b1010101110 &
0"
#102000
1"
#106000
b1 %
#109000
b10101011100 &
0"
#110000
1"
#114000
b10 %
#116000
1#
#117000
b1010111001 &
0"
#118000
1"
#122000
b11 %
#125000
b10101110011 &
0"
#126000
1"
#130000
b100 %
#133000
b1011100111 &
0"
#134000
1"
#138000
b101 %
#140000
0#
#141000
b10111001110 &
0"
#142000
1"
#146000
b110 %
#149000
b1110011100 &
0"
#150000
1"
#154000
b111 %
#156000
1#
#157000
b11100111001 &
0"
#158000
1"
#162000
b1000 %
#164000
0#
#165000
b11001110010 &
0"
#166000
1"
#170000
b1001 %
#172000
1#
#173000
b10011100101 &
0"
#174000
1"
#178000
b1010 %
#181000
b111001011 &
0"
#182000
1"
#186000
b1011 %
#196000
b0 %
b10 $
#198000
0#
#199000
b1110010110 &
0"
#200000
1"
#204000
b1 %
#207000
b11100101100 &
0"
#208000
1"
#212000
b10 %
#215000
b11001011000 &
0"
#216000
1"
#220000
b11 %
#223000
b10010110000 &
0"
#224000
1"
#228000
b100 %
#231000
b101100000 &
0"
#232000
1"
#236000
b101 %
#238000
1#
#239000
b1011000001 &
0"
#240000
1"
#244000
b110 %
#247000
b10110000011 &
0"
#248000
1"
#252000
b111 %
#255000
b1100000111 &
0"
#256000
1"
#260000
b1000 %
#263000
b11000001111 &
0"
#264000
1"
#268000
b1001 %
#271000
b10000011111 &
0"
#272000
1"
#276000
b1010 %
#279000
b111111 &
0"
#280000
1"
#284000
b1011 %
#294000
b0 %
b11 $
#296000
0#
#297000
b1111110 &
0"
#298000
1"
#302000
b1 %
#305000
b11111100 &
0"
#306000
1"
#310000
b10 %
#313000
b111111000 &
0"
#314000
1"
#318000
b11 %
#321000
b1111110000 &
0"
#322000
1"
#326000
b100 %
#329000
b11111100000 &
0"
#330000
1"
#334000
b101 %
#337000
b11111000000 &
0"
#338000
1"
#342000
b110 %
#344000
1#
#345000
b11110000001 &
0"
#346000
1"
#350000
b111 %
#353000
b11100000011 &
0"
#354000
1"
#358000
b1000 %
#361000
b11000000111 &
0"
#362000
1"
#366000
b1001 %
#368000
0#
#369000
b10000001110 &
0"
#370000
1"
#374000
b1010 %
#376000
1#
#377000
b11101 &
0"
#378000
1"
#382000
b1011 %
#392000
b100 $
