keyboard/fpga/counter.v
/*
* Basic counter module
*
* Has enable, reset, and clock inputs
*
* max_val output goes high **after** MAX_VALUE has been reached and the
* counter has been reset to 0. So, when max_val is high, the counter is
* currently at 0, except when reset by rst
*/

module counter #(
    parameter MAX_VALUE = 1,
    parameter BIT_WIDTH = 1
) (
    input en,
    clk,
    rst,

    output reg                 max_val,
    output reg [BIT_WIDTH-1:0] count
);

  always @(posedge rst) begin
    max_val <= 0;
    count   <= 0;
  end

  always @(posedge clk) begin
    if (en && !rst) begin
      count <= count + 1;
      // MAX_VALUE reached
      if (count == MAX_VALUE - 1) begin
        max_val <= 1;
        count   <= 0;
      end else begin
        max_val <= 0;
      end
    end
  end

endmodule

keyboard/fpga/initial_response.v
/*
* This module controls the initial response to the keyboard necessary for the
* resetting of the PERIBOARD ps/2 keyboard. (sends code 0xFF)
*
* inputs : reset_required should go high when the keyboard sends code 0xAA and
*           code 0xFF needs to be sent
*          clk is the clock signal
*          rst will reset the module
*/

module initial_response #(
    parameter MAX_COUNT = 1,  // number of clk ticks to keep ps2_clk low
    parameter BIT_WIDTH = 1   // number of bits needed for MAX_COUNT
) (
    input reset_required,  // code 0xAA recieved
    clk,
    rst,  // reset count to 0

    output reg ps2_clk_pulldown,
    output reg ps2_data_pulldown
);

  reg                  c1_en;
  reg                  c1_rst;
  wire                 c1_max_val;
  wire [BIT_WIDTH-1:0] c1_count;

  counter #(
      .BIT_WIDTH(BIT_WIDTH),
      .MAX_VALUE(MAX_COUNT)
  ) c1 (
      .en(c1_en),
      .clk(clk),
      .rst(c1_rst),
      .max_val(c1_max_val),
      .count(c1_count)
  );

  always @(posedge reset_required) begin
    // start counting and pull down ps2_clk
    c1_en <= 1;
    ps2_clk_pulldown <= 1;
  end

  always @(posedge clk) begin
    // always reset counter if this module is reset
    c1_rst <= rst;
    if (rst) begin
      c1_en <= 0;
      ps2_clk_pulldown <= 0;
      ps2_data_pulldown <= 0;
    end

    if (c1_en) begin
      // if reached MAX_COUNT, stop counting
      if (c1_max_val) begin
        c1_en <= 0;
        c1_rst <= 1;
        ps2_clk_pulldown <= 0;
      end
    end

    // never want to pull data line low
    ps2_data_pulldown <= 0;
  end

endmodule

keyboard/fpga/receiver.v
/*
* This module contains the "receiver" used to translate the ps/2 keyboard data
* into a format that the rest of the system can use
*/

module receiver (
    input ps2_data,
    input ps2_clk,
    input rst,

    output reg [10:0] data,
    output reg        data_latch,      // used to latch data into other modules
    output reg        reset_required,  // used when 0xAA received
    output reg        release_key,     // used when 0xF0 received
    output reg        extended_code    // used when 0xE0 received
);

  reg        c1_en = 1;
  wire       c1_max_val;
  wire [3:0] c1_count;

  counter #(
      .MAX_VALUE(11),
      .BIT_WIDTH(4)
  ) c1 (
      .en(c1_en),
      .clk(ps2_clk),
      .rst(rst),
      .max_val(c1_max_val),
      .count(c1_count)
  );

  always @(negedge ps2_clk, posedge c1_max_val) begin
    // shift in new bit
    if (!ps2_clk) begin
      data <= data << 1;
      data[0] <= ps2_data;
    end

    // set appropriate signal if 11 bits clocked in
    // bits come in lsb first, so data[8] is lsb
    if (c1_max_val) begin
      if (data[9:2] == 8'h55) begin  // 0xAA is actual code, but 0x55 cause of bit ordering
        reset_required <= 1;
      end else if (data[9:2] == 8'h0F) begin  // 0xF0
        release_key <= 1;
      end else if (data[9:2] == 8'h07) begin  // 0xE0
        extended_code <= 1;
      end else begin
        data_latch <= 1;
      end

      // else set all output signals to 0
    end else begin
      reset_required <= 0;
      release_key <= 0;
      extended_code <= 0;
      data_latch <= 0;
    end
  end

endmodule

keyboard/fpga/testbenches/reset_keyboard_tb.v
/*
* A testbench for the initial_response module
*/

`timescale 1 ns / 1 ps

module reset_keyboard_tb ();
  reg            ps2_data = 1;
  reg            ps2_clock = 1;
  reg            rst = 0;
  reg            clk = 0;
  wire    [10:0] data;
  wire           data_latch;
  wire           reset_required;
  wire           release_key;
  wire           extended_code;

  reg     [10:0] read_data      [0:0];
  integer        i;
  integer        j;

  receiver #() r (
      .ps2_data(ps2_data),
      .ps2_clk(ps2_clock),
      .rst(rst),
      .data(data),
      .data_latch(data_latch),
      .reset_required(reset_required),
      .release_key(release_key),
      .extended_code(extended_code)
  );

  initial_response #(
      .MAX_COUNT(15),
      .BIT_WIDTH(4)
  ) ir (
      .clk(clk),
      .rst(rst),
      .reset_required(reset_required)
  );

  always begin
    #1 clk = ~clk;
  end

  initial begin
    #1 rst = 1;
    #1 rst = 0;

    $readmemb("testbenches/io/reset_keyboard_io.txt", read_data);

    for (j = 0; j < 11; j = j + 1) begin
      #2 ps2_data = read_data[0][10-j];
      #1 ps2_clock = 0;
      #1 ps2_clock = 1;
      #4;
    end

    #50 $finish;
  end

  initial begin
    $dumpfile("reset_keyboard.vcd");
    $dumpvars(0, reset_keyboard_tb);
  end

endmodule

keyboard/fpga/waveforms/reset_keyboard.vcd
$date
	Fri Jul 21 23:23:06 2023
$end
$version
	Icarus Verilog
$end
$timescale
	1ps
$end
$scope module reset_keyboard_tb $end
$var wire 1 ! reset_required $end
$var wire 1 " release_key $end
$var wire 1 # extended_code $end
$var wire 1 $ data_latch $end
$var wire 11 % data [10:0] $end
$var reg 1 & clk $end
$var reg 1 ' ps2_clock $end
$var reg 1 ( ps2_data $end
$var reg 1 ) rst $end
$var integer 32 * j [31:0] $end
$scope module ir $end
$var wire 1 & clk $end
$var wire 1 ) rst $end
$var wire 1 ! reset_required $end
$var wire 1 + c1_max_val $end
$var wire 4 , c1_count [3:0] $end
$var parameter 32 - BIT_WIDTH $end
$var parameter 32 . MAX_COUNT $end
$var reg 1 / c1_en $end
$var reg 1 0 c1_rst $end
$var reg 1 1 ps2_clk_pulldown $end
$var reg 1 2 ps2_data_pulldown $end
$scope module c1 $end
$var wire 1 & clk $end
$var wire 1 / en $end
$var wire 1 0 rst $end
$var parameter 32 3 BIT_WIDTH $end
$var parameter 32 4 MAX_VALUE $end
$var reg 4 5 count [3:0] $end
$var reg 1 + max_val $end
$upscope $end
$upscope $end
$scope module r $end
$var wire 1 ' ps2_clk $end
$var wire 1 ( ps2_data $end
$var wire 1 ) rst $end
$var wire 1 6 c1_max_val $end
$var wire 4 7 c1_count [3:0] $end
$var reg 1 8 c1_en $end
$var reg 11 9 data [10:0] $end
$var reg 1 $ data_latch $end
$var reg 1 # extended_code $end
$var reg 1 " release_key $end
$var reg 1 ! reset_required $end
$scope module c1 $end
$var wire 1 ' clk $end
$var wire 1 8 en $end
$var wire 1 ) rst $end
$var parameter 32 : BIT_WIDTH $end
$var parameter 32 ; MAX_VALUE $end
$var reg 4 < count [3:0] $end
$var reg 1 6 max_val $end
$upscope $end
$upscope $end
$upscope $end
$enddefinitions $end
$comment Show the parameter values. $end
$dumpall
b1011 ;
b100 :
b1111 4
b100 3
b1111 .
b100 -
$end
#0
$dumpvars
bx <
bx 9
18
bx 7
06
bx 5
x2
x1
x0
x/
bx ,
x+
bx *
0)
1(
1'
0&
bx %
x$
x#
x"
x!
$end
#1000
b0 ,
b0 5
0+
b0 7
b0 <
02
01
0/
10
1)
1&
#2000
b0 *
0)
0&
#3000
00
1&
#4000
0&
0(
#5000
0$
0#
0"
0!
bx0 %
bx0 9
1&
0'
#6000
b1 7
b1 <
0&
1'
#7000
1&
#8000
0&
#9000
1&
#10000
0&
b1 *
#11000
1&
#12000
0&
#13000
bx00 %
bx00 9
1&
0'
#14000
b10 7
b10 <
0&
1'
#15000
1&
#16000
0&
#17000
1&
#18000
0&
b10 *
#19000
1&
#20000
0&
1(
#21000
bx001 %
bx001 9
1&
0'
#22000
b11 7
b11 <
0&
1'
#23000
1&
#24000
0&
#25000
1&
#26000
0&
b11 *
#27000
1&
#28000
0&
0(
#29000
bx0010 %
bx0010 9
1&
0'
#30000
b100 7
b100 <
0&
1'
#31000
1&
#32000
0&
#33000
1&
#34000
0&
b100 *
#35000
1&
#36000
0&
1(
#37000
bx00101 %
bx00101 9
1&
0'
#38000
b101 7
b101 <
0&
1'
#39000
1&
#40000
0&
#41000
1&
#42000
0&
b101 *
#43000
1&
#44000
0&
0(
#45000
bx001010 %
bx001010 9
1&
0'
#46000
b110 7
b110 <
0&
1'
#47000
1&
#48000
0&
#49000
1&
#50000
0&
b110 *
#51000
1&
#52000
0&
1(
#53000
bx0010101 %
bx0010101 9
1&
0'
#54000
b111 7
b111 <
0&
1'
#55000
1&
#56000
0&
#57000
1&
#58000
0&
b111 *
#59000
1&
#60000
0&
0(
#61000
bx00101010 %
bx00101010 9
1&
0'
#62000
b1000 7
b1000 <
0&
1'
#63000
1&
#64000
0&
#65000
1&
#66000
0&
b1000 *
#67000
1&
#68000
0&
1(
#69000
bx001010101 %
bx001010101 9
1&
0'
#70000
b1001 7
b1001 <
0&
1'
#71000
1&
#72000
0&
#73000
1&
#74000
0&
b1001 *
#75000
1&
#76000
0&
#77000
bx0010101011 %
bx0010101011 9
1&
0'
#78000
b1010 7
b1010 <
0&
1'
#79000
1&
#80000
0&
#81000
1&
#82000
0&
b1010 *
#83000
1&
#84000
0&
#85000
b101010111 %
b101010111 9
1&
0'
#86000
11
1/
1!
16
b0 7
b0 <
0&
1'
#87000
b1 ,
b1 5
1&
#88000
0&
#89000
b10 ,
b10 5
1&
#90000
0&
b1011 *
#91000
b11 ,
b11 5
1&
#92000
0&
#93000
b100 ,
b100 5
1&
#94000
0&
#95000
b101 ,
b101 5
1&
#96000
0&
#97000
b110 ,
b110 5
1&
#98000
0&
#99000
b111 ,
b111 5
1&
#100000
0&
#101000
b1000 ,
b1000 5
1&
#102000
0&
#103000
b1001 ,
b1001 5
1&
#104000
0&
#105000
b1010 ,
b1010 5
1&
#106000
0&
#107000
b1011 ,
b1011 5
1&
#108000
0&
#109000
b1100 ,
b1100 5
1&
#110000
0&
#111000
b1101 ,
b1101 5
1&
#112000
0&
#113000
b1110 ,
b1110 5
1&
#114000
0&
#115000
1+
b0 ,
b0 5
1&
#116000
0&
#117000
0+
b0 ,
b0 5
01
10
0/
1&
#118000
0&
#119000
00
1&
